{
  "0": {
    "basicblocks": 9,
    "calls": "1",
    "file": "BackGrRemoval.cpp",
    "fileloc": 73,
    "instructions": 9699,
    "loads": {
      "L": 3904
    },
    "name": "BackGrRemoval",
    "stores": {
      "T": 121
    },
    "total_instructions": 11317
  },
  "1": {
    "basicblocks": 391,
    "calls": "",
    "file": "RGB2HSV.cpp",
    "fileloc": 22,
    "instructions": 1618,
    "loads": {
      "L": 4
    },
    "name": "findHSV",
    "stores": {
      "L": 276
    },
    "total_instructions": 1618
  }
}