<?xml version="1.0" encoding="utf-8"?>
<Messages>
	<Message severity="INFO" prefix="[HLS 200-111]" key="HLS_111_966" tag="RUNTIME" content="Finished File checks and directory preparation: CPU user time: 0.05 seconds. CPU system time: 0.01 seconds. Elapsed time: 0.05 seconds; current allocated memory: 189.754 MB." resolution=""/>
	<Message severity="INFO" prefix="[HLS 200-10]" key="HLS_10_1312" tag="" content="Analyzing design file &apos;BaGr_ObjDetect.cpp&apos; ..." resolution=""/>
	<Message severity="INFO" prefix="[HLS 200-10]" key="HLS_10_1312" tag="" content="Analyzing design file &apos;BackGrRemoval.cpp&apos; ..." resolution=""/>
	<Message severity="WARNING" prefix="[HLS 214-111]" key="HLS 214-111" tag="DATAFLOW,VITIS_THROUGHPUT" content="Static scalars and arrays declared inside a dataflow region will be treated like local variables (BackGrRemoval.cpp:19:12)" resolution="http://www.xilinx.com/cgi-bin/docs/rdoc?v=2023.1;t=hls+guidance;d=214-111.html"/>
	<Message severity="WARNING" prefix="[HLS 214-114]" key="HLS 214-114" tag="DATAFLOW,VITIS_THROUGHPUT" content="Since the only kind of statements allowed in a canonical dataflow region are variable declarations and function calls, the compiler may not be able to correctly handle the region (BackGrRemoval.cpp:16:9)" resolution="http://www.xilinx.com/cgi-bin/docs/rdoc?v=2023.1;t=hls+guidance;d=214-114.html"/>
	<Message severity="WARNING" prefix="[HLS 200-471]" key="HLS 200-471" tag="DATAFLOW,VITIS_THROUGHPUT" content="Dataflow form checks found 2 issue(s) in file BackGrRemoval.cpp" resolution="http://www.xilinx.com/cgi-bin/docs/rdoc?v=2023.1;t=hls+guidance;d=200-471.html"/>
	<Message severity="INFO" prefix="[HLS 200-10]" key="HLS_10_1312" tag="" content="Analyzing design file &apos;RGB2HSV.cpp&apos; ..." resolution=""/>
	<Message severity="INFO" prefix="[HLS 200-10]" key="HLS_10_1312" tag="" content="Analyzing design file &apos;obj_detect.cpp&apos; ..." resolution=""/>
	<Message severity="INFO" prefix="[HLS 200-111]" key="HLS_111_966" tag="RUNTIME" content="Finished Source Code Analysis and Preprocessing: CPU user time: 8.24 seconds. CPU system time: 1.1 seconds. Elapsed time: 9.35 seconds; current allocated memory: 191.555 MB." resolution=""/>
	<Message severity="INFO" prefix="[HLS 200-777]" key="HLS 200-777" tag="" content="Using interface defaults for &apos;Vivado&apos; flow target." resolution=""/>
	<Message severity="INFO" prefix="[HLS 200-1995]" key="HLS 200-1995" tag="" content="There were 10,673 instructions in the design after the &apos;Compile/Link&apos; phase of compilation. See the Design Size Report for more details: /home/dell3561-49/Vitis_HLS_folder/BaGrRe_ObjDetect/BaGrRe_ObjDetect/solution1/syn/report/csynth_design_size.rpt" resolution=""/>
	<Message severity="INFO" prefix="[HLS 200-1995]" key="HLS 200-1995" tag="" content="There were 1,710 instructions in the design after the &apos;Unroll/Inline&apos; phase of compilation. See the Design Size Report for more details: /home/dell3561-49/Vitis_HLS_folder/BaGrRe_ObjDetect/BaGrRe_ObjDetect/solution1/syn/report/csynth_design_size.rpt" resolution=""/>
	<Message severity="INFO" prefix="[HLS 200-1995]" key="HLS 200-1995" tag="" content="There were 1,482 instructions in the design after the &apos;Performance/Pipeline&apos; phase of compilation. See the Design Size Report for more details: /home/dell3561-49/Vitis_HLS_folder/BaGrRe_ObjDetect/BaGrRe_ObjDetect/solution1/syn/report/csynth_design_size.rpt" resolution=""/>
	<Message severity="INFO" prefix="[HLS 214-131]" key="HLS 214-131" tag="" content="Inlining function &apos;Minof3(ap_uint&lt;8&gt;, ap_uint&lt;8&gt;, ap_uint&lt;8&gt;)&apos; into &apos;BackGrRemovalStream(hls::stream&lt;hls::axis&lt;ap_uint&lt;24&gt;, 1ul, 1ul, 1ul&gt;, 0&gt;&amp;, hls::stream&lt;hls::axis&lt;ap_uint&lt;24&gt;, 1ul, 1ul, 1ul&gt;, 0&gt;&amp;)&apos; (BackGrRemoval.cpp:37:26)" resolution=""/>
	<Message severity="INFO" prefix="[HLS 214-131]" key="HLS 214-131" tag="" content="Inlining function &apos;MaxOf3(ap_uint&lt;8&gt;, ap_uint&lt;8&gt;, ap_uint&lt;8&gt;)&apos; into &apos;BackGrRemovalStream(hls::stream&lt;hls::axis&lt;ap_uint&lt;24&gt;, 1ul, 1ul, 1ul&gt;, 0&gt;&amp;, hls::stream&lt;hls::axis&lt;ap_uint&lt;24&gt;, 1ul, 1ul, 1ul&gt;, 0&gt;&amp;)&apos; (BackGrRemoval.cpp:36:26)" resolution=""/>
	<Message severity="INFO" prefix="[HLS 214-131]" key="HLS 214-131" tag="" content="Inlining function &apos;uf_find(ap_uint&lt;16&gt;*, ap_uint&lt;16&gt;)&apos; into &apos;uf_union(ap_uint&lt;16&gt;*, ap_uint&lt;16&gt;, ap_uint&lt;16&gt;)&apos; (obj_detect.cpp:38:19)" resolution=""/>
	<Message severity="INFO" prefix="[HLS 214-131]" key="HLS 214-131" tag="" content="Inlining function &apos;uf_find(ap_uint&lt;16&gt;*, ap_uint&lt;16&gt;)&apos; into &apos;uf_union(ap_uint&lt;16&gt;*, ap_uint&lt;16&gt;, ap_uint&lt;16&gt;)&apos; (obj_detect.cpp:39:19)" resolution=""/>
	<Message severity="INFO" prefix="[HLS 214-131]" key="HLS 214-131" tag="" content="Inlining function &apos;is_green_rgb(ap_uint&lt;8&gt;, ap_uint&lt;8&gt;, ap_uint&lt;8&gt;)&apos; into &apos;hls_object_green_classification(hls::stream&lt;hls::axis&lt;ap_uint&lt;24&gt;, 1ul, 1ul, 1ul&gt;, 0&gt;&amp;, hls::stream&lt;hls::axis&lt;ap_uint&lt;24&gt;, 1ul, 1ul, 1ul&gt;, 0&gt;&amp;, short*, short*, ap_uint&lt;1&gt;*, ap_uint&lt;16&gt;&amp;)&apos; (obj_detect.cpp:259:31)" resolution=""/>
	<Message severity="INFO" prefix="[HLS 214-131]" key="HLS 214-131" tag="" content="Inlining function &apos;uf_find(ap_uint&lt;16&gt;*, ap_uint&lt;16&gt;)&apos; into &apos;hls_object_green_classification(hls::stream&lt;hls::axis&lt;ap_uint&lt;24&gt;, 1ul, 1ul, 1ul&gt;, 0&gt;&amp;, hls::stream&lt;hls::axis&lt;ap_uint&lt;24&gt;, 1ul, 1ul, 1ul&gt;, 0&gt;&amp;, short*, short*, ap_uint&lt;1&gt;*, ap_uint&lt;16&gt;&amp;)&apos; (obj_detect.cpp:197:29)" resolution=""/>
	<Message severity="INFO" prefix="[HLS 214-131]" key="HLS 214-131" tag="" content="Inlining function &apos;uf_union(ap_uint&lt;16&gt;*, ap_uint&lt;16&gt;, ap_uint&lt;16&gt;)&apos; into &apos;hls_object_green_classification(hls::stream&lt;hls::axis&lt;ap_uint&lt;24&gt;, 1ul, 1ul, 1ul&gt;, 0&gt;&amp;, hls::stream&lt;hls::axis&lt;ap_uint&lt;24&gt;, 1ul, 1ul, 1ul&gt;, 0&gt;&amp;, short*, short*, ap_uint&lt;1&gt;*, ap_uint&lt;16&gt;&amp;)&apos; (obj_detect.cpp:168:42)" resolution=""/>
	<Message severity="INFO" prefix="[HLS 214-291]" key="HLS 214-291" tag="" content="Loop &apos;Pass1_5_inner1&apos; is marked as complete unroll implied by the pipeline pragma (obj_detect.cpp:182:25)" resolution=""/>
	<Message severity="INFO" prefix="[HLS 214-291]" key="HLS 214-291" tag="" content="Loop &apos;Pass1_5_inner2&apos; is marked as complete unroll implied by the pipeline pragma (obj_detect.cpp:183:26)" resolution=""/>
	<Message severity="INFO" prefix="[HLS 214-291]" key="HLS 214-291" tag="" content="Loop &apos;VITIS_LOOP_51_1&apos; is marked as complete unroll implied by the pipeline pragma (BackGrRemoval.cpp:51:30)" resolution=""/>
	<Message severity="INFO" prefix="[HLS 214-291]" key="HLS 214-291" tag="" content="Loop &apos;kernel_loop&apos; is marked as complete unroll implied by the pipeline pragma (BackGrRemoval.cpp:61:26)" resolution=""/>
	<Message severity="INFO" prefix="[HLS 214-186]" key="HLS 214-186" tag="" content="Unrolling loop &apos;Pass1_5_inner1&apos; (obj_detect.cpp:182:25) in function &apos;hls_object_green_classification&apos; completely with a factor of 3 (obj_detect.cpp:50:0)" resolution=""/>
	<Message severity="INFO" prefix="[HLS 214-186]" key="HLS 214-186" tag="" content="Unrolling loop &apos;Pass1_5_inner2&apos; (obj_detect.cpp:183:26) in function &apos;hls_object_green_classification&apos; completely with a factor of 3 (obj_detect.cpp:50:0)" resolution=""/>
	<Message severity="INFO" prefix="[HLS 214-186]" key="HLS 214-186" tag="" content="Unrolling loop &apos;Shift_window&apos; (obj_detect.cpp:136:17) in function &apos;hls_object_green_classification&apos; completely with a factor of 3 (obj_detect.cpp:50:0)" resolution=""/>
	<Message severity="INFO" prefix="[HLS 214-186]" key="HLS 214-186" tag="" content="Unrolling loop &apos;VITIS_LOOP_51_1&apos; (BackGrRemoval.cpp:51:30) in function &apos;BackGrRemovalStream&apos; completely with a factor of 10 (BackGrRemoval.cpp:12:0)" resolution=""/>
	<Message severity="INFO" prefix="[HLS 214-186]" key="HLS 214-186" tag="" content="Unrolling loop &apos;kernel_loop&apos; (BackGrRemoval.cpp:61:26) in function &apos;BackGrRemovalStream&apos; completely with a factor of 11 (BackGrRemoval.cpp:12:0)" resolution=""/>
	<Message severity="INFO" prefix="[HLS 214-248]" key="HLS 214-248" tag="" content="Applying array_partition to &apos;_ZZ31hls_object_green_classificationRN3hls6streamINS_4axisI7ap_uintILi24EELm1ELm1ELm1EEELi0EEES6_PsS7_PS2_ILi1EERS2_ILi16EEE7linebuf&apos;: Complete partitioning on dimension 1. (obj_detect.cpp:111:0)" resolution=""/>
	<Message severity="INFO" prefix="[HLS 214-248]" key="HLS 214-248" tag="" content="Applying array_partition to &apos;_ZZ19BackGrRemovalStreamRN3hls6streamINS_4axisI7ap_uintILi24EELm1ELm1ELm1EEELi0EEES6_E6h_line&apos;: Complete partitioning on dimension 1. (BackGrRemoval.cpp:19:0)" resolution=""/>
	<Message severity="INFO" prefix="[HLS 214-270]" key="HLS 214-270" tag="" content="Inferring pragma &apos;array_partition type=cyclic factor=3 dim=1&apos; for array &apos;hls_object_green_classification(hls::stream&lt;hls::axis&lt;ap_uint&lt;24&gt;, 1ul, 1ul, 1ul&gt;, 0&gt;&amp;, hls::stream&lt;hls::axis&lt;ap_uint&lt;24&gt;, 1ul, 1ul, 1ul&gt;, 0&gt;&amp;, short*, short*, ap_uint&lt;1&gt;*, ap_uint&lt;16&gt;&amp;)::edge_mask&apos; due to pipeline pragma (obj_detect.cpp:180:9)" resolution=""/>
	<Message severity="INFO" prefix="[HLS 214-270]" key="HLS 214-270" tag="" content="Inferring pragma &apos;array_partition type=cyclic factor=3 dim=2&apos; for array &apos;hls_object_green_classification(hls::stream&lt;hls::axis&lt;ap_uint&lt;24&gt;, 1ul, 1ul, 1ul&gt;, 0&gt;&amp;, hls::stream&lt;hls::axis&lt;ap_uint&lt;24&gt;, 1ul, 1ul, 1ul&gt;, 0&gt;&amp;, short*, short*, ap_uint&lt;1&gt;*, ap_uint&lt;16&gt;&amp;)::edge_mask&apos; due to pipeline pragma (obj_detect.cpp:180:9)" resolution=""/>
	<Message severity="INFO" prefix="[HLS 214-248]" key="HLS 214-248" tag="" content="Applying array_partition to &apos;_ZZ31hls_object_green_classificationRN3hls6streamINS_4axisI7ap_uintILi24EELm1ELm1ELm1EEELi0EEES6_PsS7_PS2_ILi1EERS2_ILi16EEE9edge_mask&apos;: Cyclic partitioning with factor 3 on dimension 1. Cyclic partitioning with factor 3 on dimension 2. (obj_detect.cpp:75:0)" resolution=""/>
	<Message severity="ERROR" prefix="[HLS 214-208]" key="HLS 214-208" tag="" content="The ap_axis|ap_axiu|qdma_axis|hls::axis data types must only be used for AXI-Stream ports in the interface. &apos;BaGr_ObjDetect(hls::stream&lt;hls::axis&lt;ap_uint&lt;24&gt;, 1ul, 1ul, 1ul&gt;, 0&gt;&amp;, hls::stream&lt;hls::axis&lt;ap_uint&lt;24&gt;, 1ul, 1ul, 1ul&gt;, 0&gt;&amp;, short*, short*, ap_uint&lt;1&gt;*, ap_uint&lt;16&gt;&amp;)::mid_stream&apos; is not an AXI-Stream and/or is not a port in the interface" resolution=""/>
	<Message severity="ERROR" prefix="[HLS 200-1715]" key="HLS 200-1715" tag="" content="Encountered problem during source synthesis" resolution=""/>
	<Message severity="INFO" prefix="[HLS 200-111]" key="HLS_111_966" tag="RUNTIME" content="Finished Command csynth_design CPU user time: 10.7 seconds. CPU system time: 1.35 seconds. Elapsed time: 16.39 seconds; current allocated memory: 3.547 MB." resolution=""/>
</Messages>
